{
    "array": [
        {
            "id": "squad_demon_t4_t5_t6_25",
            "useOldSquads": false,
            "rollChance": 54,
            "canBeMainGuard": false,
            "baseSquad": {
                "units": [
                    {
                        "s": "jaw_upg_alt",
                        "v": 6026
                    },
                    {
                        "s": "godslayer_upg_alt",
                        "v": 9186
                    },
                    {
                        "s": "olgoi",
                        "v": 14026
                    }
                ]
            },
            "dynamicSquad": {
                "requiredValue": 14026,
                "units": [
                    "jaw_upg_alt",
                    "godslayer_upg_alt",
                    "olgoi"
                ]
            },
            "randomSquad": {
                "maxValue": 80026,
                "units": [
                    {
                        "s": "jaw_upg_alt",
                        "v": 30356
                    },
                    {
                        "s": "godslayer_upg_alt",
                        "v": 47356
                    },
                    {
                        "s": "olgoi",
                        "v": 80026
                    }
                ]
            },
            "tier": 6,
            "fraction": "demon"
        }
    ]
}