{
	"array": [
		{
			"id": "M1Q1_dial6",
			"localization": true,
			"slides": [
				{
					"id": "start",
					"fon": "",
					"avatars": [
						{
							"position": 1,
							"icon": "icons/dialogue/dialogue_hero_6_gunnar",
							"isForeground": "true",
							"animations": ["zoomIn"]
						},
						{
							"position": 5,
							"icon": "icons/dialogue/dialogue_unit_peasant",
							"isForeground": "false",
							"animations": ["zoomOut"]
						}
					],
					"title": {
						"sid": "dialogue_title_hero_dungeon",
						"position": 1
					},
					"text": "dialogue_text_M1Q1_dial6_0",
					"mapActions": [
						{
							"a": "MoveCamera",
							"p": [
								"1819"
							]
						}
					],
					"next": "1"
				},
				{
					"id": "1",
					"fon": "",
					"avatars": [
						{
							"position": 1,
							"icon": "icons/dialogue/dialogue_hero_6_gunnar",
							"isForeground": "false",
							"animations": ["zoomOut"]
						},
						{
							"position": 5,
							"icon": "icons/dialogue/dialogue_unit_peasant",
							"isForeground": "true",
							"animations": ["zoomIn"]
						}
					],
					"title": {
						"sid": "dialogue_title_peasant_guide",
						"position": 2
					},
					"text": "dialogue_text_M1Q1_dial6_1",
					"next": "2"
				},
				{
					"id": "2",
					"fon": "",
					"avatars": [
						{
							"position": 1,
							"icon": "icons/dialogue/dialogue_hero_6_gunnar",
							"isForeground": "true",
							"animations": ["zoomIn"]
						},
						{
							"position": 5,
							"icon": "icons/dialogue/dialogue_unit_peasant",
							"isForeground": "false",
							"animations": ["zoomOut"]
						}
					],
					"title": {
						"sid": "dialogue_title_hero_dungeon",
						"position": 1
					},
					"text": "dialogue_text_M1Q1_dial6_2",
					"next": "3"
				},
				{
					"id": "3",
					"fon": "",
					"avatars": [
						{
							"position": 1,
							"icon": "icons/dialogue/dialogue_hero_6_gunnar",
							"isForeground": "true",
							"animations": ["zoomIn"]
						},
						{
							"position": 5,
							"icon": "icons/dialogue/dialogue_unit_peasant",
							"isForeground": "false",
							"animations": ["zoomOut"]
						}
					],
					"title": {
						"sid": "dialogue_title_hero_dungeon",
						"position": 1
					},
					"text": "dialogue_text_M1Q1_dial6_3",
					"next": "ending"
				},
				{
					"id": "ending",
					"fon": "",
					"text": "",
					"mapActions": [
						{
							"a": "DeleteEntity",
							"p": [
								"zone_final_demon"
							]
						},
						{
							"a": "AutoSave"
						}
					],
					"invokeOnlyActions": true,
					"end": true
				}
			]
		}
	]
}