{
    "array": [
        {
            "id": "squad_human_t2_t3_t5_27",
            "useOldSquads": false,
            "rollChance": 11,
            "canBeMainGuard": false,
            "baseSquad": {
                "units": [
                    {
                        "s": "crossbowman_upg_alt",
                        "v": 4185
                    },
                    {
                        "s": "griffin_upg_alt",
                        "v": 5015
                    },
                    {
                        "s": "sunlight_cavalry_upg_alt",
                        "v": 7185
                    }
                ]
            },
            "dynamicSquad": {
                "requiredValue": 7185,
                "units": [
                    "crossbowman_upg_alt",
                    "griffin_upg_alt",
                    "sunlight_cavalry_upg_alt"
                ]
            },
            "randomSquad": {
                "maxValue": 23355,
                "units": [
                    {
                        "s": "crossbowman_upg_alt",
                        "v": 8685
                    },
                    {
                        "s": "griffin_upg_alt",
                        "v": 15015
                    },
                    {
                        "s": "sunlight_cavalry_upg_alt",
                        "v": 23355
                    }
                ]
            },
            "tier": 5,
            "fraction": "human"
        }
    ]
}