{
    "array": [
        {
            "id": "squad_nature_t2_t3_t4_8",
            "useOldSquads": false,
            "rollChance": 19,
            "canBeMainGuard": false,
            "baseSquad": {
                "units": [
                    {
                        "s": "twinkle",
                        "v": 5184
                    },
                    {
                        "s": "ent_upg_alt",
                        "v": 5184
                    },
                    {
                        "s": "aqualotl_upg",
                        "v": 5184
                    }
                ]
            },
            "dynamicSquad": {
                "requiredValue": 5184,
                "units": [
                    "twinkle",
                    "ent_upg_alt",
                    "aqualotl_upg"
                ]
            },
            "randomSquad": {
                "maxValue": 20014,
                "units": [
                    {
                        "s": "twinkle",
                        "v": 8684
                    },
                    {
                        "s": "ent_upg_alt",
                        "v": 15684
                    },
                    {
                        "s": "aqualotl_upg",
                        "v": 20014
                    }
                ]
            },
            "tier": 4,
            "fraction": "nature"
        }
    ]
}