{
	"array":
	[
		{
			"id": "if_main_quest_line_wake_up",
			"localization": true,
			"slides": [
				{
					"id": "start",
					"fon": "",
					"avatars": [
						{
							"position": 1,
							"icon": "icons/dialogue/dialog_hero_unfrozen_11_Ice_Queen_Ort_large",
							"isForeground": "true",
							"animations": ["zoomIn"]
						}
					],
					"title": {
						"sid": "unfrozen_hero_11",
						"position": 3
					},
					"text": "if_main_quest_line_wake_up_1",
					"mapActions": [ { "a": "TeleportHero", "p": [ "unfrozen_hero_11", "4095" ] }, { "a": "DeleteHero", "p": [ "unfrozen_hero_11" ] }, { "a": "MoveCamera", "p": [ "2194" ] }, { "a": "SpawnHero", "p": [ "unfrozen_hero_11", "4095", "0" ] }, { "a": "TeleportHero", "p": [ "unfrozen_hero_11", "2194" ] } ],
					"next": "1"
				},
				{
					"id": "1",
					"fon": "",
					"avatars": [
						{
							"position": 1,
							"icon": "icons/dialogue/dialog_hero_unfrozen_11_Ice_Queen_Ort_large",
							"isForeground": "false",
							"animations": ["zoomOut"]
						},
						{
							"position": 5,
							"icon": "icons/dialogue/dialog_frostworm_rider_upg",
							"isForeground": "true",
							"animations": ["zoomIn"]
						}
					],
					"title": {
						"sid": "infinity_frost_hero_1",
						"position": 3
					},
					"text": "if_main_quest_line_wake_up_2",
					"next": "2"
				},
				{
					"id": "2",
					"fon": "",
					"avatars": [
						{
							"position": 1,
							"icon": "icons/dialogue/dialog_hero_unfrozen_11_Ice_Queen_Ort_large",
							"isForeground": "true",
							"animations": ["zoomIn"]
						},
						{
							"position": 5,
							"icon": "icons/dialogue/dialog_frostworm_rider_upg",
							"isForeground": "false",
							"animations": ["zoomOut"]
						}
					],
					"title": {
						"sid": "unfrozen_hero_11",
						"position": 3
					},
					"text": "if_main_quest_line_wake_up_3",
					"next": "3"
				},
				{
					"id": "3",
					"fon": "",
					"avatars": [
						{
							"position": 1,
							"icon": "icons/dialogue/dialog_hero_unfrozen_11_Ice_Queen_Ort_large",
							"isForeground": "false",
							"animations": ["zoomOut"]
						},
						{
							"position": 5,
							"icon": "icons/dialogue/dialog_frostworm_rider_upg",
							"isForeground": "true",
							"animations": ["zoomIn"]
						}
					],
					"title": {
						"sid": "infinity_frost_hero_1",
						"position": 3
					},
					"text": "if_main_quest_line_wake_up_4",
					"next": "4"
				},
				{
					"id": "4",
					"fon": "",
					"avatars": [
						{
							"position": 1,
							"icon": "icons/dialogue/dialog_hero_unfrozen_11_Ice_Queen_Ort_large",
							"isForeground": "false",
							"animations": ["zoomOut"]
						},
						{
							"position": 5,
							"icon": "icons/dialogue/dialog_frostworm_rider_upg",
							"isForeground": "true",
							"animations": ["zoomIn"]
						}
					],
					"title": {
						"sid": "infinity_frost_hero_1",
						"position": 3
					},
					"text": "if_main_quest_line_wake_up_5",
					"next": "5"
				},
				{
					"id": "5",
					"fon": "",
					"avatars": [
						{
							"position": 1,
							"icon": "icons/dialogue/dialog_hero_unfrozen_11_Ice_Queen_Ort_large",
							"isForeground": "true",
							"animations": ["zoomIn"]
						},
						{
							"position": 5,
							"icon": "icons/dialogue/dialog_frostworm_rider_upg",
							"isForeground": "false",
							"animations": ["zoomOut"]
						}
					],
					"title": {
						"sid": "unfrozen_hero_11",
						"position": 3
					},
					"text": "if_main_quest_line_wake_up_6",
					"next": "6"
				},
				{
					"id": "6",
					"fon": "",
					"avatars": [
						{
							"position": 1,
							"icon": "icons/dialogue/dialog_hero_unfrozen_11_Ice_Queen_Ort_large",
							"isForeground": "false",
							"animations": ["zoomOut"]
						},
						{
							"position": 5,
							"icon": "icons/dialogue/dialog_frostworm_rider_upg",
							"isForeground": "true",
							"animations": ["zoomIn"]
						}
					],
					"title": {
						"sid": "infinity_frost_hero_1",
						"position": 3
					},
					"text": "if_main_quest_line_wake_up_7",
					"next": "7"
				},
				{
					"id": "7",
					"fon": "",
					"avatars": [
						{
							"position": 1,
							"icon": "icons/dialogue/dialog_hero_unfrozen_11_Ice_Queen_Ort_large",
							"isForeground": "true",
							"animations": ["zoomIn"]
						},
						{
							"position": 5,
							"icon": "icons/dialogue/dialog_frostworm_rider_upg",
							"isForeground": "false",
							"animations": ["zoomOut"]
						}
					],
					"title": {
						"sid": "unfrozen_hero_11",
						"position": 3
					},
					"text": "if_main_quest_line_wake_up_8",
					"next": "8"
				},
				{
					"id": "8",
					"fon": "",
					"avatars": [
						{
							"position": 1,
							"icon": "icons/dialogue/dialog_hero_unfrozen_11_Ice_Queen_Ort_large",
							"isForeground": "true",
							"animations": ["zoomIn"]
						},
						{
							"position": 5,
							"icon": "icons/dialogue/dialog_frostworm_rider_upg",
							"isForeground": "false",
							"animations": ["zoomOut"]
						}
					],
					"title": {
						"sid": "unfrozen_hero_11",
						"position": 3
					},
					"mapActions": [ { "a": "CounterPlus", "p": [ "main_quest_save_queen", "1" ] } ],
					"text": "if_main_quest_line_wake_up_9",
					"end": true
				}
			]
		}
	]
}
