{
	"array": [
		{
			"id": "M3Q4_dial6",
			"localization": true,
			"slides": [
				{
					"id": "start",
					"dialogPlayConditions": [
						{
							"c": "Counter",
							"p": [
								"abbey_plundered",
								"=",
								"1"
							]
						}
					],
					"fon": "",
					"avatars": [
						{
							"position": 1,
							"icon": "icons/dialogue/dialogue_hero_6_gunnar",
							"isForeground": "false",
							"animations": ["zoomOut"]
						},
						{
							"position": 5,
							"icon": "icons/dialogue/dialogue_unit_lightweaver",
							"isForeground": "true",
							"animations": ["zoomIn"]
						}
					],
					"title": {
						"sid": "dialogue_title_lightweaver",
						"position": 2
					},
					"text": "dialogue_text_M3Q4_dial6_0",
					"actions": [
						{
							"a": "StoryCounterMinus",
							"p": [
								"fractionReputation_Human",
								"1"
							]
						}
					],
					"mapActions": [
						{
							"a": "ShowFloatingUI",
							"p": [
								"human_icon",
								"-1"
							]
						}
					],
					"next": "0_s"
				},
				{
					"id": "0_s",
					"fon": "",
					"text": "dialogue_text_M3Q4_dial6_0_s",
					"mapActions": [
						{
							"a": "RemoveItem",
							"p": [
								"campaign_M3_freed_priestesses_item"
							]
						}
					],
					"next": "1"
				},
				{
					"id": "1",
					"fon": "",
					"avatars": [
						{
							"position": 1,
							"icon": "icons/dialogue/dialogue_hero_6_gunnar",
							"isForeground": "true",
							"animations": ["zoomIn"]
						},
						{
							"position": 4,
							"icon": "icons/dialogue/dialogue_unit_lightweaver",
							"isForeground": "false",
							"animations": ["zoomOut"]
						},
						{
							"position": 5,
							"icon": "icons/dialogue/dialogue_unit_lightweaver",
							"isForeground": "false",
							"animations": ["zoomOut"]
						}
					],
					"title": {
						"sid": "dialogue_title_hero_dungeon",
						"position": 1
					},
					"text": "dialogue_text_M3Q4_dial6_1",
					"next": "2"
				},
				{
					"id": "2",
					"fon": "",
					"avatars": [
						{
							"position": 1,
							"icon": "icons/dialogue/dialogue_hero_6_gunnar",
							"isForeground": "false",
							"animations": ["zoomOut"]
						},
						{
							"position": 4,
							"icon": "icons/dialogue/dialogue_unit_lightweaver",
							"isForeground": "true",
							"animations": ["zoomIn"]
						},
						{
							"position": 5,
							"icon": "icons/dialogue/dialogue_unit_lightweaver",
							"isForeground": "false",
							"animations": ["zoomOut"]
						}
					],
					"title": {
						"sid": "dialogue_title_lightweaver",
						"position": 2
					},
					"text": "dialogue_text_M3Q4_dial6_2",
					"next": "2m"
				},
				{
					"id": "2m",
					"fon": "",
					"avatars": [
						{
							"position": 1,
							"icon": "icons/dialogue/dialogue_hero_6_gunnar",
							"isForeground": "false",
							"animations": ["zoomOut"]
						},
						{
							"position": 4,
							"icon": "icons/dialogue/dialogue_unit_lightweaver",
							"isForeground": "false",
							"animations": ["zoomOut"]
						},
						{
							"position": 5,
							"icon": "icons/dialogue/dialogue_unit_lightweaver",
							"isForeground": "true",
							"animations": ["zoomIn"]
						}
					],
					"title": {
						"sid": "dialogue_title_lightweaver",
						"position": 2
					},
					"text": "dialogue_text_M3Q4_dial6_2m",
					"next": "2m_s"
				},
				{
					"id": "2m_s",
					"fon": "",
					"text": "dialogue_text_M3Q4_dial6_2m_s",
					"mapActions": [
						{
							"a": "AddSpellHero",
							"p": [
								"day_3_magic_haste",
								"campaign_hero_1"
							]
						}
					],
					"next": "3"
				},
				{
					"id": "3",
					"fon": "",
					"avatars": [
						{
							"position": 1,
							"icon": "icons/dialogue/dialogue_hero_6_gunnar",
							"isForeground": "false",
							"animations": ["zoomOut"]
						},
						{
							"position": 4,
							"icon": "icons/dialogue/dialogue_unit_lightweaver",
							"isForeground": "true",
							"animations": ["zoomIn"]
						},
						{
							"position": 5,
							"icon": "icons/dialogue/dialogue_unit_lightweaver",
							"isForeground": "false",
							"animations": ["zoomOut"]
						}
					],
					"title": {
						"sid": "dialogue_title_lightweaver",
						"position": 2
					},
					"text": "dialogue_text_M3Q4_dial6_3",
					"next": "4"
				},
				{
					"id": "4",
					"fon": "",
					"avatars": [
						{
							"position": 1,
							"icon": "icons/dialogue/dialogue_hero_6_gunnar",
							"isForeground": "false",
							"animations": ["zoomOut"]
						},
						{
							"position": 4,
							"icon": "icons/dialogue/dialogue_unit_lightweaver",
							"isForeground": "false",
							"animations": ["zoomOut"]
						},
						{
							"position": 5,
							"icon": "icons/dialogue/dialogue_unit_lightweaver",
							"isForeground": "true",
							"animations": ["zoomIn"]
						}
					],
					"title": {
						"sid": "dialogue_title_lightweaver",
						"position": 2
					},
					"text": "dialogue_text_M3Q4_dial6_4",
					"next": "5"
				},
				{
					"id": "5",
					"fon": "",
					"avatars": [
						{
							"position": 1,
							"icon": "icons/dialogue/dialogue_hero_6_gunnar",
							"isForeground": "false",
							"animations": ["zoomOut"]
						},
						{
							"position": 4,
							"icon": "icons/dialogue/dialogue_unit_lightweaver",
							"isForeground": "true",
							"animations": ["zoomIn"]
						},
						{
							"position": 5,
							"icon": "icons/dialogue/dialogue_unit_lightweaver",
							"isForeground": "false",
							"animations": ["zoomOut"]
						}
					],
					"title": {
						"sid": "dialogue_title_lightweaver",
						"position": 2
					},
					"text": "dialogue_text_M3Q4_dial6_5",
					"next": "6"
				},
				{
					"id": "6",
					"fon": "",
					"avatars": [
						{
							"position": 1,
							"icon": "icons/dialogue/dialogue_hero_6_gunnar",
							"isForeground": "true",
							"animations": ["zoomIn"]
						},
						{
							"position": 4,
							"icon": "icons/dialogue/dialogue_unit_lightweaver",
							"isForeground": "false",
							"animations": ["zoomOut"]
						},
						{
							"position": 5,
							"icon": "icons/dialogue/dialogue_unit_lightweaver",
							"isForeground": "false",
							"animations": ["zoomOut"]
						}
					],
					"title": {
						"sid": "dialogue_title_hero_dungeon",
						"position": 1
					},
					"text": "dialogue_text_M3Q4_dial6_6",
					"next": "ending"
				},
				{
					"id": "ending",
					"fon": "",
					"text": "",
					"actions": [
						{
							"a": "StoryCounterPlus",
							"p": [
								"fractionReputation_Human",
								"1"
							]
						}
					],
					"mapActions": [
						{
							"a": "ShowFloatingUI",
							"p": [
								"human_icon",
								"+1"
							]
						},						
						{
							"a": "CounterSet",
							"p": [
								"priestess_quest",
								"4"
							]
						}
					],
					"invokeOnlyActions": true,
					"end": true,
					"resultDialog": "Interrupt"
				}
			]
		}
	]
}