{
	"array": [
		{
			"id": "M9Q5_dial6",
			"localization": true,
			"slides": [
				{
					"id": "start",
					"fon": "",
					"avatars": [
						{
							"position": 1,
							"icon": "icons/dialogue/dialogue_hero_6_gunnar",
							"isForeground": "false",
							"animations": ["zoomOut"]
						},
						{
							"position": 2,
							"icon": "icons/dialogue/dialogue_hero_2_lafiur",
							"isForeground": "false",
							"animations": ["zoomOut"]
						},
						{
							"position": 5,
							"icon": "icons/dialogue/dialogue_unit_elf_tracker_upg_alt",
							"isForeground": "true",
							"animations": ["zoomIn"]
						}
					],
					"title": {
						"sid": "dialogue_title_sylvan_captain",
						"position": 2
					},
					"text": "dialogue_text_M9Q5_dial6_0",
					"mapActions":
					[
						{ "a": "CounterSet", "p": [ "sylvan_captain_seen", "1" ] }
					],
					"next": "1"
				},
				{
					"id": "1",
					"fon": "",
					"avatars": [
						{
							"position": 1,
							"icon": "icons/dialogue/dialogue_hero_6_gunnar",
							"isForeground": "false",
							"animations": ["zoomOut"]
						},
						{
							"position": 2,
							"icon": "icons/dialogue/dialogue_hero_2_lafiur",
							"isForeground": "false",
							"animations": ["zoomOut"]
						},
						{
							"position": 5,
							"icon": "icons/dialogue/dialogue_unit_elf_tracker_upg_alt",
							"isForeground": "true",
							"animations": ["zoomIn"]
						}
					],
					"title": {
						"sid": "dialogue_title_sylvan_captain",
						"position": 2
					},
					"text": "dialogue_text_M9Q5_dial6_1",
					"next": "2"
				},
				{
					"id": "2",
					"fon": "",
					"avatars": [
						{
							"position": 1,
							"icon": "icons/dialogue/dialogue_hero_6_gunnar",
							"isForeground": "false",
							"animations": ["zoomOut"]
						},
						{
							"position": 2,
							"icon": "icons/dialogue/dialogue_hero_2_lafiur",
							"isForeground": "false",
							"animations": ["zoomOut"]
						},
						{
							"position": 5,
							"icon": "icons/dialogue/dialogue_unit_elf_tracker_upg_alt",
							"isForeground": "true",
							"animations": ["zoomIn"]
						}
					],
					"title": {
						"sid": "dialogue_title_sylvan_captain",
						"position": 2
					},
					"text": "dialogue_text_M9Q5_dial6_2",
					"next": "2m"
				},
				{
					"id": "2m",
					"fon": "",
					"avatars": [
						{
							"position": 1,
							"icon": "icons/dialogue/dialogue_hero_6_gunnar",
							"isForeground": "false",
							"animations": ["zoomOut"]
						},
						{
							"position": 2,
							"icon": "icons/dialogue/dialogue_hero_2_lafiur",
							"isForeground": "true",
							"animations": ["zoomIn"]
						},
						{
							"position": 5,
							"icon": "icons/dialogue/dialogue_unit_elf_tracker_upg_alt",
							"isForeground": "false",
							"animations": ["zoomOut"]
						}
					],
					"title": {
						"sid": "dialogue_title_hero_nature",
						"position": 1
					},
					"text": "dialogue_text_M9Q5_dial6_2m",
					"next": "2m1"
				},
				{
					"id": "2m1",
					"fon": "",
					"avatars": [
						{
							"position": 1,
							"icon": "icons/dialogue/dialogue_hero_6_gunnar",
							"isForeground": "true",
							"animations": ["zoomIn"]
						},
						{
							"position": 2,
							"icon": "icons/dialogue/dialogue_hero_2_lafiur",
							"isForeground": "false",
							"animations": ["zoomOut"]
						},
						{
							"position": 5,
							"icon": "icons/dialogue/dialogue_unit_elf_tracker_upg_alt",
							"isForeground": "false",
							"animations": ["zoomOut"]
						}
					],
					"title": {
						"sid": "dialogue_title_hero_dungeon",
						"position": 1
					},
					"text": "dialogue_text_M2Q3_dial2_2a",
					"answers": [
						{
							"text": "dialogue_text_M9Q5_dial6_2_answer_1",
							"requests": [
								{
									"c": "Counter",
									"p": [
										"heard_sylvans_plan",
										"=",
										"0"
									]
								}
							],
							"actions": [
								{
									"a": "StoryCounterPlus",
									"p": [
										"fractionReputation_Nature",
										"1"
									]
								},
								{
									"a": "StoryCounterMinus",
									"p": [
										"fractionReputation_Human",
										"1"
									]
								},
								{
									"a": "Go",
									"p": [
										"2a"
									]
								}
							],
							"mapActions": [
								{
									"a": "ShowFloatingUI",
									"p": [
										"human_icon",
										"-1"
									]
								},
								{
									"a": "ShowFloatingUI",
									"p": [
										"spring_icon",
										"+1"
									]
								},
								{
									"a": "CounterSet",
									"p": [
										"heard_sylvans_plan",
										"1"
									]
								}
							]
						},
						{
							"text": "dialogue_text_M9Q5_dial6_2a2_answer_1",
							"requests": [
								{
									"c": "Counter",
									"p": [
										"heard_sylvans_plan",
										"=",
										"1"
									]
								}
							],
							"actions": [
								{
									"a": "Go",
									"p": [
										"2a2a"
									]
								}
							]
						},
						{
							"text": "dialogue_text_M9Q5_dial6_2_answer_2",
							"requests": [
								{
									"c": "Counter",
									"reqStatus": "false",
									"p": [
										"forest_quest",
										"=",
										"1"
									]
								}
							],
							"actions": [
								{
									"a": "Go",
									"p": [
										"2b"
									]
								}
							]
						},
						{
							"text": "dialogue_text_M9Q5_dial6_2_answer_3",
							"actions": [
								{
									"a": "Go",
									"p": [
										"2c"
									]
								}
							]
						}
					]
				},
				{
					"id": "2a",
					"fon": "",
					"avatars": [
						{
							"position": 1,
							"icon": "icons/dialogue/dialogue_hero_6_gunnar",
							"isForeground": "false",
							"animations": ["zoomOut"]
						},
						{
							"position": 2,
							"icon": "icons/dialogue/dialogue_hero_2_lafiur",
							"isForeground": "false",
							"animations": ["zoomOut"]
						},
						{
							"position": 5,
							"icon": "icons/dialogue/dialogue_unit_elf_tracker_upg_alt",
							"isForeground": "true",
							"animations": ["zoomIn"]
						}
					],
					"title": {
						"sid": "dialogue_title_sylvan_captain",
						"position": 2
					},
					"text": "dialogue_text_M9Q5_dial6_2a",
					"next": "2a1"
				},
				{
					"id": "2a1",
					"fon": "",
					"avatars": [
						{
							"position": 1,
							"icon": "icons/dialogue/dialogue_hero_6_gunnar",
							"isForeground": "false",
							"animations": ["zoomOut"]
						},
						{
							"position": 2,
							"icon": "icons/dialogue/dialogue_hero_2_lafiur",
							"isForeground": "false",
							"animations": ["zoomOut"]
						},
						{
							"position": 5,
							"icon": "icons/dialogue/dialogue_unit_elf_tracker_upg_alt",
							"isForeground": "true",
							"animations": ["zoomIn"]
						}
					],
					"title": {
						"sid": "dialogue_title_sylvan_captain",
						"position": 2
					},
					"text": "dialogue_text_M9Q5_dial6_2a1",
					"mapActions": [
						{
							"a": "MoveCamera",
							"p": [
								"4697"
							]
						},
						{
							"a": "RevealFogOfWar",
							"p": [
								"4697",
								"2"
							]
						}
					],
					"next": "2a2"
				},
				{
					"id": "2a2",
					"fon": "",
					"avatars": [
						{
							"position": 1,
							"icon": "icons/dialogue/dialogue_hero_6_gunnar",
							"isForeground": "false",
							"animations": ["zoomOut"]
						},
						{
							"position": 2,
							"icon": "icons/dialogue/dialogue_hero_2_lafiur",
							"isForeground": "false",
							"animations": ["zoomOut"]
						},
						{
							"position": 5,
							"icon": "icons/dialogue/dialogue_unit_elf_tracker_upg_alt",
							"isForeground": "true",
							"animations": ["zoomIn"]
						}
					],
					"title": {
						"sid": "dialogue_title_sylvan_captain",
						"position": 2
					},
					"text": "dialogue_text_M9Q5_dial6_2a2",
					"mapActions": [
						{
							"a": "MoveCamera",
							"p": [
								"4114"
							]
						}
					],
					"answers": [
						{
							"text": "dialogue_text_M9Q5_dial6_2a2_answer_1",
							"actions": [
								{
									"a": "Go",
									"p": [
										"2a2a"
									]
								}
							]
						},
						{
							"text": "dialogue_text_M9Q5_dial6_2a2_answer_2",
							"requests": [
								{
									"c": "Counter",
									"reqStatus": "false",
									"p": [
										"forest_quest",
										"=",
										"1"
									]
								}
							],
							"actions": [
								{
									"a": "StoryCounterMinus",
									"p": [
										"fractionReputation_Nature",
										"1"
									]
								},
								{
									"a": "Go",
									"p": [
										"2b"
									]
								}
							],
							"mapActions": [
								{
									"a": "ShowFloatingUI",
									"p": [
										"spring_icon",
										"-1"
									]
								}
							]
						},
						{
							"text": "dialogue_text_M9Q5_dial6_2a2_answer_2",
							"requests": [
								{
									"c": "Counter",
									"reqStatus": "true",
									"p": [
										"forest_quest",
										"=",
										"1"
									]
								}
							],
							"actions": [
								{
									"a": "StoryCounterMinus",
									"p": [
										"fractionReputation_Nature",
										"1"
									]
								},
								{
									"a": "Go",
									"p": [
										"2c"
									]
								}
							],
							"mapActions": [
								{
									"a": "ShowFloatingUI",
									"p": [
										"spring_icon",
										"-1"
									]
								}
							]
						}
					]
				},
				{
					"id": "2a2a",
					"fon": "",
					"avatars": [
						{
							"position": 1,
							"icon": "icons/dialogue/dialogue_hero_6_gunnar",
							"isForeground": "false",
							"animations": ["zoomOut"]
						},
						{
							"position": 2,
							"icon": "icons/dialogue/dialogue_hero_2_lafiur",
							"isForeground": "false",
							"animations": ["zoomOut"]
						},
						{
							"position": 5,
							"icon": "icons/dialogue/dialogue_unit_elf_tracker_upg_alt",
							"isForeground": "true",
							"animations": ["zoomIn"]
						}
					],
					"title": {
						"sid": "dialogue_title_sylvan_captain",
						"position": 2
					},
					"text": "dialogue_text_M9Q5_dial6_2a2a",
					"next": "2a2a1"
				},
				{
					"id": "2a2a1",
					"fon": "",
					"avatars": [
						{
							"position": 1,
							"icon": "icons/dialogue/dialogue_hero_6_gunnar",
							"isForeground": "false",
							"animations": ["zoomOut"]
						},
						{
							"position": 2,
							"icon": "icons/dialogue/dialogue_hero_2_lafiur",
							"isForeground": "false",
							"animations": ["zoomOut"]
						},
						{
							"position": 5,
							"icon": "icons/dialogue/dialogue_unit_elf_tracker_upg_alt",
							"isForeground": "true",
							"animations": ["zoomIn"]
						}
					],
					"title": {
						"sid": "dialogue_title_sylvan_captain",
						"position": 2
					},
					"text": "dialogue_text_M9Q5_dial6_2a2a1",
					"mapActions": [
						{
							"a": "MoveCamera",
							"p": [
								"4394"
							]
						},
						{
							"a": "RevealFogOfWar",
							"p": [
								"4394",
								"2"
							]
						}
					],
					"next": "endHelpSylvan"
				},
				{
					"id": "endHelpSylvan",
					"fon": "",
					"text": "",
					"invokeOnlyActions": true,
					"mapActions": [
						{
							"a": "CounterSet",
							"p": [
								"forest_quest",
								"2"
							]
						},
						{
							"a": "StepBack"
						},
						{
							"a": "SetActiveQuestMarker",
							"p": [
								"sylvan_grove",
								"false"
							]
						}
					],
					"resultDialog": "Interrupt",
					"end": true
				},
				{
					"id": "2b",
					"fon": "",
					"avatars": [
						{
							"position": 1,
							"icon": "icons/dialogue/dialogue_hero_6_gunnar",
							"isForeground": "false",
							"animations": ["zoomOut"]
						},
						{
							"position": 2,
							"icon": "icons/dialogue/dialogue_hero_2_lafiur",
							"isForeground": "false",
							"animations": ["zoomOut"]
						},
						{
							"position": 5,
							"icon": "icons/dialogue/dialogue_unit_elf_tracker_upg_alt",
							"isForeground": "true",
							"animations": ["zoomIn"]
						}
					],
					"title": {
						"sid": "dialogue_title_sylvan_captain",
						"position": 2
					},
					"text": "dialogue_text_M9Q5_dial6_2b",
					"next": "endingPeace"
				},
				{
					"id": "2c",
					"fon": "",
					"avatars": [
						{
							"position": 1,
							"icon": "icons/dialogue/dialogue_hero_6_gunnar",
							"isForeground": "false",
							"animations": ["zoomOut"]
						},
						{
							"position": 2,
							"icon": "icons/dialogue/dialogue_hero_2_lafiur",
							"isForeground": "false",
							"animations": ["zoomOut"]
						},
						{
							"position": 5,
							"icon": "icons/dialogue/dialogue_unit_elf_tracker_upg_alt",
							"isForeground": "true",
							"animations": ["zoomIn"]
						}
					],
					"title": {
						"sid": "dialogue_title_sylvan_captain",
						"position": 2
					},
					"text": "dialogue_text_M9Q5_dial6_2c",
					"next": "2c1"
				},
				{
					"id": "2c1",
					"fon": "",
					"avatars": [
						{
							"position": 1,
							"icon": "icons/dialogue/dialogue_hero_6_gunnar",
							"isForeground": "false",
							"animations": ["zoomOut"]
						},
						{
							"position": 2,
							"icon": "icons/dialogue/dialogue_hero_2_lafiur",
							"isForeground": "false",
							"animations": ["zoomOut"]
						},
						{
							"position": 5,
							"icon": "icons/dialogue/dialogue_unit_elf_tracker_upg_alt",
							"isForeground": "true",
							"animations": ["zoomIn"]
						}
					],
					"title": {
						"sid": "dialogue_title_sylvan_captain",
						"position": 2
					},
					"text": "dialogue_text_M9Q5_dial6_2c1",
					"next": "endingFight"
				},
				{
					"id": "endingFight",
					"fon": "",
					"text": "",
					"mapActions": [
						{
							"a": "InitiateAttack",
							"p": [
								"sylvan_grove"
							]
						}
					],
					"invokeOnlyActions": true,
					"end": true,
					"resultDialog": "Interrupt"
				},
				{
					"id": "endingPeace",
					"fon": "",
					"text": "",
					"invokeOnlyActions": true,
					"mapActions": [
						{
							"a": "StepBack"
						}
					],
					"end": true,
					"resultDialog": "Interrupt"
				}
			]
		}
	]
}